{"9nQTP93D9xIoGLZC47TJug==":"mbr-900x581.jpg","NipmdyqQ/PJHVqCMB7Ksew==":"galaxy.avif","Oal3aOu6i+QoDC1g1Pfjcg==":"nft-7004985-1920-900x500.jpg","5GRzBE02diISRxUd1pTyjQ==":"profile-410x410.jpg","/YWjh6fNp3VtF5LsVVOOfw==":"logo.svg","vKpaYJ8bXACQrbgfJJSyVg==":"personaje-900x761.png","/8j18su/ROgAMN1W4LBtBw==":"logo.png","MAvpcwmafpnHuXu7Jc15Yg==":"logo_test-900x802.jpg","h7hAUFde47o7rXBTHY05dg==":"logo_test-900x802.jpeg","9G5Pt7OCuFNrc4d0CvUbgA==":"coin_bleton-720x1280.jpeg","GEkOFnF4TPcen/V4bP4g7g==":"bleton_hand-717x856.png","j9YkhWvcil+Ul3gz66z1mQ==":"photo_2022-06-24_22-13-56-410x410.jpg","jhPn5Hpvpfbf/3MeuAgFUg==":"photo_2022-10-24_21-58-46-720x1280.jpg","pn1ihCI1bJBUyp0GhtBfwA==":"photo_2022-10-27_12-24-44-853x1280.jpg","xHiliYojLODo49SW5/QkZg==":"photo_2022-10-22_19-03-44-900x1157.jpg","FwzNTv6Cf6mDzJ/6kMF7hQ==":"photo_2022-11-07_22-04-41-240x240.jpg"}